impetuous/__init__.py
impetuous/clustering.py
impetuous/convert.py
impetuous/fit.py
impetuous/hierarchical.py
impetuous/impetuous.py
impetuous/optimisation.py
impetuous/pathways.py
impetuous/probabilistic.py
impetuous/quantification.py
impetuous/reducer.py
impetuous/special.py
impetuous/spectral.py
impetuous/visualisation.py
impetuous_gfa-0.101.15.dist-info/LICENSE
impetuous_gfa-0.101.15.dist-info/METADATA
impetuous_gfa-0.101.15.dist-info/WHEEL
impetuous_gfa-0.101.15.dist-info/top_level.txt
impetuous_gfa-0.101.15.dist-info/RECORD
