Metadata-Version: 2.1
Name: impetuous-gfa
Version: 0.101.15
Summary: Impetuous Quantification, a Statistical Learning library for Humans : Alignments, Clustering, Fast NodeGraph Searching, Enrichments and Group Analysis
Home-page: https://github.com/richardtjornhammar/impetuous
Author: Richard Tjörnhammar
Author-email: richard.tjornhammar@gmail.com
Classifier: Programming Language :: Python :: 3
Classifier: Programming Language :: Python :: 3.7
Classifier: Programming Language :: Python :: 3.8
Classifier: Programming Language :: Python :: 3.9
Classifier: Programming Language :: Python :: 3.10
Classifier: License :: OSI Approved :: Apache Software License
Classifier: Operating System :: OS Independent
License-File: LICENSE
